meowsay.py
meowsay-1.0.2.dist-info/LICENSE
meowsay-1.0.2.dist-info/METADATA
meowsay-1.0.2.dist-info/WHEEL
meowsay-1.0.2.dist-info/entry_points.txt
meowsay-1.0.2.dist-info/top_level.txt
meowsay-1.0.2.dist-info/RECORD
