Metadata-Version: 2.1
Name: meowsay
Version: 1.0.2
Summary: Cowsay, but better.
Home-page: https://github.com/tusharsadhwani/meowsay
Author: Tushar Sadhwani
Author-email: tushar.sadhwani000@gmail.com
License: UNKNOWN
Platform: UNKNOWN
Classifier: Programming Language :: Python :: 3
Classifier: License :: OSI Approved :: MIT License
Classifier: Operating System :: OS Independent
Requires-Python: >=3.6
